dlk/__init__.py
dlk/demo.py
dlk/export.py
dlk/online.py
dlk/predict.py
dlk/preprocess.py
dlk/server.py
dlk/train.py
dlk/version.py
dlk/adv_method/__init__.py
dlk/adv_method/fgm.py
dlk/adv_method/free_lb.py
dlk/adv_method/pgd.py
dlk/callback/__init__.py
dlk/callback/checkpoint.py
dlk/callback/early_stop.py
dlk/callback/lr_monitor.py
dlk/callback/progress_bar.py
dlk/callback/weight_average.py
dlk/cuda/ngram_repeat_block_cuda.cpp
dlk/cuda/ngram_repeat_block_cuda_kernel.cu
dlk/data/__init__.py
dlk/data/data_collate/__init__.py
dlk/data/data_collate/default.py
dlk/data/datamodule/__init__.py
dlk/data/datamodule/default.py
dlk/data/dataset/__init__.py
dlk/data/dataset/default.py
dlk/data/postprocessor/__init__.py
dlk/data/postprocessor/generate_post.py
dlk/data/postprocessor/identity.py
dlk/data/postprocessor/img_cls.py
dlk/data/postprocessor/seq_lab.py
dlk/data/postprocessor/span_cls.py
dlk/data/postprocessor/span_relation.py
dlk/data/postprocessor/txt_cls.py
dlk/data/postprocessor/txt_reg.py
dlk/data/processor/__init__.py
dlk/data/processor/default.py
dlk/data/subprocessor/__init__.py
dlk/data/subprocessor/char_gather.py
dlk/data/subprocessor/fast_tokenizer.py
dlk/data/subprocessor/image_process.py
dlk/data/subprocessor/piece_rerank_relabel.py
dlk/data/subprocessor/seq_lab_firstpiece_relabel.py
dlk/data/subprocessor/seq_lab_relabel.py
dlk/data/subprocessor/span_cls_relabel.py
dlk/data/subprocessor/span_relation_relabel.py
dlk/data/subprocessor/token2charid.py
dlk/data/subprocessor/token2id.py
dlk/data/subprocessor/token_embedding.py
dlk/data/subprocessor/token_gather.py
dlk/data/subprocessor/token_norm.py
dlk/display/__init__.py
dlk/display/img_caption.py
dlk/display/img_cls.py
dlk/display/relation_extract.py
dlk/display/seq_lab.py
dlk/display/summary.py
dlk/display/txt_cls.py
dlk/display/txt_reg.py
dlk/imodel/__init__.py
dlk/imodel/default.py
dlk/initmethod/__init__.py
dlk/initmethod/default.py
dlk/initmethod/range_norm.py
dlk/initmethod/range_uniform.py
dlk-0.1.3.dist-info/LICENSE
dlk-0.1.3.dist-info/METADATA
dlk-0.1.3.dist-info/WHEEL
dlk-0.1.3.dist-info/top_level.txt
dlk-0.1.3.dist-info/RECORD
