Metadata-Version: 2.1
Name: dlk
Version: 0.1.3
Summary: dlk: Deep Learning Kit
Home-page: https://github.com/cstsunfu/dlk
Author-email: cstsunfu <cstsunfu@gmail.com>
License: Copyright 2021 cstsunfu
Keywords: dlk,pytorch,lightning
Classifier: Programming Language :: Python
Classifier: Programming Language :: Python :: 3
Classifier: Programming Language :: Python :: 3 :: Only
Classifier: License :: OSI Approved :: Apache Software License
Requires-Python: >=3.7
License-File: LICENSE
Requires-Dist: intc <0.2,>=0.1.1
Requires-Dist: hjson >=3.0.2
Requires-Dist: pandas >=1.4
Requires-Dist: fsspec <2024.2,>=2023.5
Requires-Dist: torchmetrics >=1.2.1
Requires-Dist: pyarrow >=10.0.1
Requires-Dist: transformers <4.45,>=4.37.0
Provides-Extra: all
Requires-Dist: lightning <=2.2,>=2.1.0 ; extra == 'all'
Requires-Dist: torch <=2.6,>=2.1 ; extra == 'all'
Requires-Dist: tensorboard <3.0,>=2.7.0 ; extra == 'all'
Requires-Dist: datasets <2.20,>=2.17.0 ; extra == 'all'
Requires-Dist: streamlit >=1.32 ; extra == 'all'
Requires-Dist: svgwrite >=1.4 ; extra == 'all'
Requires-Dist: pyecharts >=2.0 ; extra == 'all'
Provides-Extra: export
Requires-Dist: torch <=2.6,>=1.8.1 ; extra == 'export'
Provides-Extra: process
Requires-Dist: datasets <2.20,>=2.17.0 ; extra == 'process'
Provides-Extra: train
Requires-Dist: lightning <=2.2,>=2.1.0 ; extra == 'train'
Requires-Dist: torch <=2.6,>=2.1 ; extra == 'train'
Requires-Dist: tensorboard <3.0,>=2.7.0 ; extra == 'train'
Requires-Dist: datasets <2.20,>=2.17.0 ; extra == 'train'
Requires-Dist: torchmetrics >=1.2.1 ; extra == 'train'
